normalise/__init__.py
normalise/domains.py
normalise/email.py
normalise_email-0.1.23.dist-info/LICENSE
normalise_email-0.1.23.dist-info/METADATA
normalise_email-0.1.23.dist-info/WHEEL
normalise_email-0.1.23.dist-info/RECORD
